gpt_repl/__init__.py
gpt_repl/__main__.py
gpt_repl/cli.py
gpt_repl/config.py
gpt_repl/publish.py
gpt_repl/requirements.txt
gpt_repl/jupyter/__init__.py
gpt_repl/jupyter/kernel.py
gpt_repl/jupyter/gpt-repl/__init__.py
gpt_repl/jupyter/gpt-repl/kernel.json
gpt_repl/llms/__init__.py
gpt_repl/llms/gpt3.py
gpt_repl/llms/chat_gpt/__init__.py
gpt_repl/llms/chat_gpt/api.mjs
gpt_repl/llms/chat_gpt/chat_gpt.py
gpt_repl/modes/__init__.py
gpt_repl/modes/base_mode.py
gpt_repl/modes/chat_gpt.py
gpt_repl/modes/cowsay.py
gpt_repl/modes/echo.py
gpt_repl/modes/js_sandbox.py
gpt_repl/modes/raw_codex.py
gpt_repl/modes/raw_gpt.py
gpt_repl/modes/synth_chat.py
gpt_repl/profiles/delphi.json
gpt_repl/repl/__init__.py
gpt_repl/repl/core.py
gpt_repl/repl/pretty.py
gpt_repl/repl/prompt.py
gpt_repl/repl/search.py
gpt_repl/repl/commands/__init__.py
gpt_repl/repl/commands/base_command.py
gpt_repl/repl/commands/command_manager.py
gpt_repl/repl/commands/normal_commands.py
gpt_repl/repl/commands/special_commands.py
gpt_repl/threads/__init__.py
gpt_repl/threads/message.py
gpt_repl/threads/thread.py
gpt_repl/threads/thread_manager.py
gpt_repl/utils/__init__.py
gpt_repl/utils/editor.py
gpt_repl/utils/loader.py
gpt_repl/utils/markdown.py
gpt_repl/utils/misc.py
gpt_repl/utils/printer.py
gpt_repl/utils/server.py
gpt_repl-0.4.21.dist-info/entry_points.txt
gpt_repl-0.4.21.dist-info/LICENSE
gpt_repl-0.4.21.dist-info/WHEEL
gpt_repl-0.4.21.dist-info/METADATA
gpt_repl-0.4.21.dist-info/RECORD
