Metadata-Version: 2.1
Name: gpt-repl
Version: 0.4.21
Summary: Command line REPL for GPT-based tools
Author-email: Lucas Hansen <lucashansen@gmail.com>
Requires-Python: >=3.9
Classifier: License :: OSI Approved :: MIT License
Requires-Dist: click >=8.0
Requires-Dist: guesslang-experimental >=2.2.3
Requires-Dist: openai >=0.25
Requires-Dist: prompt_toolkit >=3.0
Requires-Dist: pyperclip >=1.0
Requires-Dist: requests >=2.0
Requires-Dist: rich >=12.0
Requires-Dist: tiktoken >=0.1
Project-URL: Home, https://github.com/veered/gpt-repl
